sonarqube_api/__init__.py
sonarqube_api/api.py
sonarqube_api/exceptions.py
sonarqube_api/sonar.py
sonarqube_api/utils.py
sonarqube_api/cmd/__init__.py
sonarqube_api/cmd/activate_rules.py
sonarqube_api/cmd/export_rules.py
sonarqube_api/cmd/migrate_rules.py
sonarqube_api/sonarapi/__init__.py
sonarqube_api/sonarapi/authentication.py
sonarqube_api/sonarapi/branches.py
sonarqube_api/sonarapi/components.py
sonarqube_api/sonarapi/groups.py
sonarqube_api/sonarapi/metrics.py
sonarqube_api/sonarapi/permissions.py
sonarqube_api/sonarapi/projects.py
sonarqube_api/sonarapi/qualitygates.py
sonarqube_api/sonarapi/qualityprofiles.py
sonarqube_api/sonarapi/resources.py
sonarqube_api/sonarapi/rules.py
sonarqube_api/sonarapi/settings.py
sonarqube_api/sonarapi/user_token.py
sonarqube_api/sonarapi/users.py
opn_sonarqube_api-2.3.3.4261112.dist-info/LICENSE
opn_sonarqube_api-2.3.3.4261112.dist-info/METADATA
opn_sonarqube_api-2.3.3.4261112.dist-info/WHEEL
opn_sonarqube_api-2.3.3.4261112.dist-info/entry_points.txt
opn_sonarqube_api-2.3.3.4261112.dist-info/top_level.txt
opn_sonarqube_api-2.3.3.4261112.dist-info/RECORD
