Metadata-Version: 2.1
Name: opn-sonarqube-api
Version: 2.3.3.4261112
Summary: Open SonarQube API Handler
Home-page: UNKNOWN
Author: open sas
Author-email: boost-support@open-groupe.com
License: MIT
Keywords: api sonar sonarqube
Platform: UNKNOWN
Classifier: Development Status :: 5 - Production/Stable
Classifier: Environment :: Plugins
Classifier: Intended Audience :: Developers
Classifier: License :: OSI Approved :: MIT License
Classifier: Operating System :: OS Independent
Classifier: Programming Language :: Python :: 2.7
Classifier: Programming Language :: Python :: 3.4
Classifier: Programming Language :: Python :: 3.5
Classifier: Programming Language :: Python :: 3.6
Classifier: Topic :: Software Development
Requires-Dist: requests (<2.99,>=2.9)
